py_tegra_swizzle-0.4.1.dist-info/RECORD
py_tegra_swizzle-0.4.1.dist-info/LICENSE
py_tegra_swizzle-0.4.1.dist-info/WHEEL
py_tegra_swizzle-0.4.1.dist-info/top_level.txt
py_tegra_swizzle-0.4.1.dist-info/METADATA
py_tegra_swizzle/version.py
py_tegra_swizzle/__init__.py
py_tegra_swizzle/rust.abi3.so
py_tegra_swizzle/rust.pyi
