Metadata-Version: 2.1
Name: py-tegra-swizzle
Version: 0.4.1
Summary: Python bindings for the Rust library tegra-swizzle.
Classifier: License :: OSI Approved :: MIT License
Classifier: Development Status :: 3 - Alpha
Classifier: Intended Audience :: Developers
Classifier: Programming Language :: Python :: 3.10
Classifier: Programming Language :: Python :: 3.11
Classifier: Programming Language :: Python :: 3.12
Classifier: Programming Language :: Rust
Requires-Python: >=3.10
License-File: LICENSE
